inspiredco/__init__.py
inspiredco/client_base.py
inspiredco/critique.py
inspiredco/version.py
inspiredco/critique_utils/__init__.py
inspiredco/critique_utils/exceptions.py
inspiredco-0.0.2.dist-info/METADATA
inspiredco-0.0.2.dist-info/WHEEL
inspiredco-0.0.2.dist-info/licenses/LICENSE.txt
inspiredco-0.0.2.dist-info/RECORD
