Metadata-Version: 2.1
Name: inspiredco
Version: 0.0.2
Summary: Inspired Cognition API client
Author-email: Inspired Cognition <support@inspiredco.ai>
License: MIT
License-File: LICENSE.txt
Classifier: Programming Language :: Python :: 3.8
Classifier: Programming Language :: Python :: 3.9
Classifier: Programming Language :: Python :: 3.10
Classifier: Programming Language :: Python :: 3.11
Requires-Python: >=3.8
Requires-Dist: requests>=2.27.0
Provides-Extra: test
Requires-Dist: pytest-mock>=3.0.0; extra == 'test'
Requires-Dist: pytest>=6.0.0; extra == 'test'
